CameraSimulator/__init__.py
CameraSimulator-0.0.10.dist-info/METADATA
CameraSimulator-0.0.10.dist-info/WHEEL
CameraSimulator-0.0.10.dist-info/top_level.txt
CameraSimulator-0.0.10.dist-info/RECORD
