Metadata-Version: 2.1
Name: CameraSimulator
Version: 0.0.10
Summary: Basic Camera Emulator
Home-page: UNKNOWN
Author: David Navarro 
Author-email: <dcnavarros@unal.edu.co>
License: UNKNOWN
Keywords: python,camera,gain
Platform: UNKNOWN
Classifier: Development Status :: 1 - Planning
Classifier: Intended Audience :: Developers
Classifier: Programming Language :: Python :: 3
Classifier: Operating System :: Unix
Classifier: Operating System :: MacOS :: MacOS X
Classifier: Operating System :: Microsoft :: Windows
Requires-Dist: numpy
